fifo_buffer.v
module fifo_buffer #(
    parameter DATA_WIDTH = 8,
    parameter ADDR_WIDTH = 4,
    parameter FIFO_DEPTH = 16
) (
    input clk, reset_n,
    input write_enable,
    input [DATA_WIDTH-1:0] data_in,
    input read_enable,
    output reg [DATA_WIDTH-1:0] data_out,
    output full, empty
);

reg [DATA_WIDTH-1:0] mem_arr [0:FIFO_DEPTH-1] ;
reg [ADDR_WIDTH-1:0] write_ptr, read_ptr ;
reg [ADDR_WIDTH:0] status ; // To know how many items are there in FIFO buffer
    
always @(posedge clk) begin
    if (!reset_n) begin
        write_ptr <= 0 ;
        read_ptr <= 0 ;
        status <= 0 ;
    end else begin
        if (write_enable) begin
            if (!full) begin
                mem_arr[write_ptr] <= data_in ;
                write_ptr <= write_ptr + 1'b1 ;
            end
        end
        if (read_enable) begin
            if (!empty) begin
                data_out <= mem_arr[read_ptr] ;
                read_ptr <= read_ptr + 1'b1 ;
            end else begin
                data_out <= {DATA_WIDTH{1'b1}} ;
            end
        end
        case ({(write_enable && !full), (read_enable && !empty)})
        2'b01 : status <= status - 1 ;
        2'b10 : status <= status + 1 ;
            default: status <= status ;
        endcase
    end
end

assign full  = (status == FIFO_DEPTH) ;
assign empty = (status == 0) ;

endmodule

fifo_tb.v
`timescale 1ns/1ps

module tb_fifo_buffer;

    // Parameters
    parameter DATA_WIDTH = 8;
    parameter ADDR_WIDTH = 4;
    parameter FIFO_DEPTH = 16;

    // Testbench Signals
    reg clk;
    reg reset_n;
    reg write_enable;
    reg [DATA_WIDTH-1:0] data_in;
    reg read_enable;
    
    wire [DATA_WIDTH-1:0] data_out;
    wire full;
    wire empty;

    // Instantiate the Design Under Test (DUT)
    fifo_buffer #(
        .DATA_WIDTH(DATA_WIDTH),
        .ADDR_WIDTH(ADDR_WIDTH),
        .FIFO_DEPTH(FIFO_DEPTH)
    ) uut (
        .clk(clk),
        .reset_n(reset_n),
        .write_enable(write_enable),
        .data_in(data_in),
        .read_enable(read_enable),
        .data_out(data_out),
        .full(full),
        .empty(empty)
    );

    // Clock Generation (50 MHz Clock -> 20ns period)
    always #10 clk = ~clk;

    // Task for Writing Data
    task write_data(input [DATA_WIDTH-1:0] val);
        begin
            @(posedge clk);
            write_enable = 1;
            data_in = val;
            #1; // Small delay to check flags after edge
        end
    endtask

    // Task for Reading Data
    task read_data;
        begin
            @(posedge clk);
            write_enable = 0; // Ensure we aren't writing
            read_enable = 1;
            #1;
        end
    endtask

    // Stimulus Block
    initial begin
        // Initialize Signals
        $dumpfile("fifo_wave.vcd");
        $dumpvars(0, tb_fifo_buffer);
        
        clk = 0;
        reset_n = 0;
        write_enable = 0;
        read_enable = 0;
        data_in = 0;

        // 1. Reset Test
        #40;
        reset_n = 1;
        $display("[TIME %0t] Reset released. Empty flag: %b (Expected: 1)", $time, empty);

        // 2. Fill the FIFO to the max (16 writes)
        $display("\n--- Starting Write Test ---");
        repeat(FIFO_DEPTH) begin
            write_data($random % 256);
        end
        
        // Turn off write enable and check full flag
        @(posedge clk);
        write_enable = 0;
        #1;
        $display("[TIME %0t] Finished 16 writes. Full flag: %b (Expected: 1)", $time, full);

        // Try 1 extra write to prove it safely rejects it
        // write_data(8'hFF);
        @(posedge clk);
        write_enable = 0;

        // 3. Read everything back out (16 reads)
        $display("\n--- Starting Read Test ---");
        repeat(FIFO_DEPTH) begin
            read_data();
            $display("[TIME %0t] Read Data Out: %h", $time, data_out);
        end
        
        // Turn off read enable and check empty flag
        @(posedge clk);
        read_enable = 0;
        #1;
        $display("[TIME %0t] Finished 16 reads. Empty flag: %b (Expected: 1)", $time, empty);

        // 4. Simultaneous Read and Write Stress Test
        $display("\n--- Starting Simultaneous R/W Test ---");
        // Put 2 items in first
        write_data(8'hAA);
        write_data(8'hBB);
        
        // Execute R/W on the same edge
        @(posedge clk);
        write_enable = 1;
        read_enable = 1;
        data_in = 8'hCC; // Writing CC while reading AA
        
        #1;
        $display("[TIME %0t] Sim R/W - Out: %h (Expected: aa), Status Counter shouldn't change.", $time, data_out);
        
        @(posedge clk);
        write_enable = 0;
        read_enable = 0;

        #100;
        $display("\nSimulation Completed Successfully!");
        $finish;
    end

endmodule

fifo_wave.vcd
$date
	Mon Jun  8 17:27:10 2026
$end
$version
	Icarus Verilog
$end
$timescale
	1ps
$end
$scope module tb_fifo_buffer $end
$var wire 1 ! full $end
$var wire 1 " empty $end
$var wire 8 # data_out [7:0] $end
$var parameter 32 $ ADDR_WIDTH $end
$var parameter 32 % DATA_WIDTH $end
$var parameter 32 & FIFO_DEPTH $end
$var reg 1 ' clk $end
$var reg 8 ( data_in [7:0] $end
$var reg 1 ) read_enable $end
$var reg 1 * reset_n $end
$var reg 1 + write_enable $end
$scope module uut $end
$var wire 1 ' clk $end
$var wire 8 , data_in [7:0] $end
$var wire 1 ) read_enable $end
$var wire 1 * reset_n $end
$var wire 1 + write_enable $end
$var wire 1 ! full $end
$var wire 1 " empty $end
$var parameter 32 - ADDR_WIDTH $end
$var parameter 32 . DATA_WIDTH $end
$var parameter 32 / FIFO_DEPTH $end
$var reg 8 0 data_out [7:0] $end
$var reg 4 1 read_ptr [3:0] $end
$var reg 5 2 status [4:0] $end
$var reg 4 3 write_ptr [3:0] $end
$upscope $end
$scope task read_data $end
$upscope $end
$scope task write_data $end
$var reg 8 4 val [7:0] $end
$upscope $end
$upscope $end
$enddefinitions $end
$comment Show the parameter values. $end
$dumpall
b10000 /
b1000 .
b100 -
b10000 &
b1000 %
b100 $
$end
#0
$dumpvars
bx 4
bx 3
bx 2
bx 1
bx 0
b0 ,
0+
0*
0)
b0 (
0'
bx #
x"
x!
$end
#10000
0!
1"
b0 2
b0 1
b0 3
1'
#20000
0'
#30000
1'
#40000
0'
b100100 4
1*
#50000
0"
b1 2
b1 3
b100100 (
b100100 ,
1+
1'
#51000
b10000001 4
#60000
0'
#70000
b10 2
b10 3
b10000001 (
b10000001 ,
1'
#71000
b1001 4
#80000
0'
#90000
b11 2
b11 3
b1001 (
b1001 ,
1'
#91000
b1100011 4
#100000
0'
#110000
b100 2
b100 3
b1100011 (
b1100011 ,
1'
#111000
b1101 4
#120000
0'
#130000
b101 2
b101 3
b1101 (
b1101 ,
1'
#131000
b10001101 4
#140000
0'
#150000
b110 2
b110 3
b10001101 (
b10001101 ,
1'
#151000
b1100101 4
#160000
0'
#170000
b111 2
b111 3
b1100101 (
b1100101 ,
1'
#171000
b10010 4
#180000
0'
#190000
b1000 2
b1000 3
b10010 (
b10010 ,
1'
#191000
b1 4
#200000
0'
#210000
b1001 2
b1001 3
b1 (
b1 ,
1'
#211000
b1101 4
#220000
0'
#230000
b1010 2
b1010 3
b1101 (
b1101 ,
1'
#231000
b1110110 4
#240000
0'
#250000
b1011 2
b1011 3
b1110110 (
b1110110 ,
1'
#251000
b111101 4
#260000
0'
#270000
b1100 2
b1100 3
b111101 (
b111101 ,
1'
#271000
b11101101 4
#280000
0'
#290000
b1101 2
b1101 3
b11101101 (
b11101101 ,
1'
#291000
b10001100 4
#300000
0'
#310000
b1110 2
b1110 3
b10001100 (
b10001100 ,
1'
#311000
b11111001 4
#320000
0'
#330000
b1111 2
b1111 3
b11111001 (
b11111001 ,
1'
#331000
b11000110 4
#340000
0'
#350000
1!
b10000 2
b0 3
b11000110 (
b11000110 ,
1'
#360000
0'
#370000
0+
1'
#380000
0'
#390000
1'
#400000
0'
#410000
0!
b1111 2
b1 1
b100100 #
b100100 0
1)
1'
#420000
0'
#430000
b1110 2
b10 1
b10000001 #
b10000001 0
1'
#440000
0'
#450000
b1101 2
b11 1
b1001 #
b1001 0
1'
#460000
0'
#470000
b1100 2
b100 1
b1100011 #
b1100011 0
1'
#480000
0'
#490000
b1011 2
b101 1
b1101 #
b1101 0
1'
#500000
0'
#510000
b1010 2
b110 1
b10001101 #
b10001101 0
1'
#520000
0'
#530000
b1001 2
b111 1
b1100101 #
b1100101 0
1'
#540000
0'
#550000
b1000 2
b1000 1
b10010 #
b10010 0
1'
#560000
0'
#570000
b111 2
b1001 1
b1 #
b1 0
1'
#580000
0'
#590000
b110 2
b1010 1
b1101 #
b1101 0
1'
#600000
0'
#610000
b101 2
b1011 1
b1110110 #
b1110110 0
1'
#620000
0'
#630000
b100 2
b1100 1
b111101 #
b111101 0
1'
#640000
0'
#650000
b11 2
b1101 1
b11101101 #
b11101101 0
1'
#660000
0'
#670000
b10 2
b1110 1
b10001100 #
b10001100 0
1'
#680000
0'
#690000
b1 2
b1111 1
b11111001 #
b11111001 0
1'
#700000
0'
#710000
1"
b0 2
b0 1
b11000110 #
b11000110 0
1'
#720000
0'
#730000
0)
1'
#731000
b10101010 4
#740000
0'
#750000
0"
b1 2
b1 3
b10101010 (
b10101010 ,
1+
1'
#751000
b10111011 4
#760000
0'
#770000
b10 2
b10 3
b10111011 (
b10111011 ,
1'
#780000
0'
#790000
b1 1
b10101010 #
b10101010 0
b11 3
b11001100 (
b11001100 ,
1)
1'
#800000
0'
#810000
0)
0+
1'
